mobiliteit_api/__init__.py
mobiliteit_api/api.py
mobiliteit_api-0.0.1.dist-info/LICENSE
mobiliteit_api-0.0.1.dist-info/METADATA
mobiliteit_api-0.0.1.dist-info/WHEEL
mobiliteit_api-0.0.1.dist-info/top_level.txt
mobiliteit_api-0.0.1.dist-info/RECORD
