Metadata-Version: 2.1
Name: mobiliteit_api
Version: 0.0.1
Summary: Allows making calls to the Mobiliteit.lu API from python.
Author-email: Felix3qH4 <weiterleitung4@gmail.com>
Project-URL: Homepage, http://github.com/Felix3qH4/Mobiliteit.lu-Python-API
Project-URL: Bug Tracker, http://github.com/Felix3qH4/Mobiliteit.lu-Python-API/issues
Classifier: Programming Language :: Python :: 3
Classifier: License :: OSI Approved :: MIT License
Classifier: Operating System :: OS Independent
Requires-Python: >=3.7
License-File: LICENSE
